models_files_manager/__init__.py
models_files_manager/models_files_manager.py
models_files_manager-1.0.5.dist-info/LICENSE
models_files_manager-1.0.5.dist-info/METADATA
models_files_manager-1.0.5.dist-info/WHEEL
models_files_manager-1.0.5.dist-info/top_level.txt
models_files_manager-1.0.5.dist-info/RECORD
