Metadata-Version: 2.1
Name: models-files-manager
Version: 1.0.5
Summary: Manage saved models files, encode fields into filenames
Author-email: Ram Nathaniel <ram.nathaniel@gmail.com>
License: MIT License
Project-URL: repository, https://github.com/RamNathaniel/models-files-manager
Project-URL: documentation, https://ramnathaniel.github.io/models-files-manager
Keywords: deep,learning,models,files,manager
Classifier: License :: OSI Approved :: MIT License
Classifier: Programming Language :: Python
Classifier: Programming Language :: Python :: 3
Requires-Python: >=3.7
License-File: LICENSE
Requires-Dist: tomli ; python_version < "3.11"
Provides-Extra: dev
Requires-Dist: pip-tools ; extra == 'dev'
Requires-Dist: mypy ; extra == 'dev'
Requires-Dist: pytest ; extra == 'dev'
